mnk_persian_words/__init__.py
mnk_persian_words/persian_words.py
mnk_persian_words-1.0.2.dist-info/METADATA
mnk_persian_words-1.0.2.dist-info/WHEEL
mnk_persian_words-1.0.2.dist-info/top_level.txt
mnk_persian_words-1.0.2.dist-info/RECORD
