Metadata-Version: 2.4
Name: mnk_persian_words
Version: 1.0.2
Summary: Creates REALLY random Persian words
Home-page: https://github.com/masoudnk/PersianWordsLib
Author: Masoud Najafzadeh Kalat
Author-email: masoudnk2@gmail.com
License: MIT
Classifier: Programming Language :: Python :: 3
Classifier: License :: OSI Approved :: MIT License
Classifier: Operating System :: OS Independent
Classifier: Natural Language :: Persian
Requires-Python: >=3.7
Dynamic: author
Dynamic: author-email
Dynamic: classifier
Dynamic: description
Dynamic: description-content-type
Dynamic: home-page
Dynamic: license
Dynamic: requires-python
Dynamic: summary
